src/__init__.py
src/main.py
src/messages/__init__.py
src/messages/all_messages.py
src/messages/tomodachi.py
dinner_at_clemz-0.0.2.dist-info/METADATA
dinner_at_clemz-0.0.2.dist-info/WHEEL
dinner_at_clemz-0.0.2.dist-info/entry_points.txt
dinner_at_clemz-0.0.2.dist-info/top_level.txt
dinner_at_clemz-0.0.2.dist-info/RECORD
