Metadata-Version: 2.1
Name: dinner-at-clemz
Version: 0.0.2
Summary: dinner_at_clementi is a python package that is essential for launching the next scalable unicorn in South East Asia.
Home-page: https://github.com/chrishendra93/dinner_at_clemz
Author: meja_bundar_dover_crescent
Maintainer-email: dinner_at_clementi@gmail.com
License: MIT
Platform: UNKNOWN
Classifier: Development Status :: 5 - Production/Stable
Classifier: License :: OSI Approved :: MIT License
Classifier: Programming Language :: Python
Classifier: Programming Language :: Python :: 3.8
Classifier: Topic :: Software Development :: Libraries
Classifier: Intended Audience :: Other Audience
Requires-Python: >=3.5
